{"name":"JDeveloper Copyright Plugin","body":"This is an attempt to provide similar functionality to [Intellij's Copyright Plugin][intellij] from within JDeveloper.\r\n\r\nYou can read more in the [blog post][blog_post]\r\n\r\n## Installation\r\n### Check for Updates Bundle\r\n1. Start JDev\r\n2. Go to Help -> Check for Update -> Add\r\n3. Enter the following into the add dialog\r\n   Name: Whatever_You_Want \r\n   Location: https://raw.github.com/jacobdanner/jdev-copyright-plugin/master/center.xml\r\n4. Select extension and install\r\n5. Restart JDeveloper\r\n\r\n### Local Install\r\n1. Download the [Bundle Jar][bundlejar]\r\n2. Go to Help -> Check for Update -> Install from Local File\r\n3. Select the file you just downloaded.\r\n4. Restart JDeveloper\r\n\r\n## How to Use\r\nThe extension is pretty simple once its installed\r\n\r\n1. Go to Tools -> Preferences -> Copyright\r\n2. Modify the copyright text\r\n3. Select File(s) in the navigator menu\r\n   Right Click \r\n   Select Insert Copyright\r\n\r\nThat's it :)\r\n\r\n[center.xml]:https://raw.github.com/jacobdanner/jdev-copyright-plugin/master/center.xml \"JDeveloper Copyright Plugin\"\r\n[intellij]:http://www.jetbrains.com/idea/webhelp/generating-and-updating-copyright-notice.html       \"Intellij's Copyright Plugin\"\r\n[bundlejar]: https://github.com/jacobdanner/jdev-copyright-plugin/blob/master/com.ph477y.jdev.copyright_bundle.zip?raw=true \"bundle jar\"\r\n[blog_post]: http://g33kd0m.ph477y.com/2011/11/jdeveloper-copyright-plugin.html    \"blog post\"","tagline":"A simple plugin for JDeveloper that will add copyright/license info","google":"","note":"Don't delete this file! It's used internally to help with page regeneration."}